print_on_steroids/__init__.py
print_on_steroids/get_frame.py
print_on_steroids/print.py
print_on_steroids-1.2.3.dist-info/LICENSE
print_on_steroids-1.2.3.dist-info/METADATA
print_on_steroids-1.2.3.dist-info/WHEEL
print_on_steroids-1.2.3.dist-info/top_level.txt
print_on_steroids-1.2.3.dist-info/zip-safe
print_on_steroids-1.2.3.dist-info/RECORD
