Metadata-Version: 2.1
Name: print-on-steroids
Version: 1.2.3
Summary: A lean & hackable rich logger and print function.
Home-page: https://github.com/konstantinjdobler/print-on-steroids
Project-URL: Bug Tracker, https://github.com/konstantinjdobler/print-on-steroids/issues
Project-URL: Changelog, https://github.com/konstantinjdobler/print-on-steroids/releases
Classifier: Programming Language :: Python :: 3
Classifier: License :: OSI Approved :: MIT License
Classifier: Intended Audience :: Developers
Requires-Python: >=3.7
License-File: LICENSE
Requires-Dist: rich
Requires-Dist: tqdm
Provides-Extra: dev
Requires-Dist: black ; extra == 'dev'
Requires-Dist: ruff ; extra == 'dev'
Provides-Extra: exceptions
Requires-Dist: better-exceptions ; extra == 'exceptions'
